{"data":[{"hovertemplate":"%{y}\u003cbr\u003e%{x:,} \u5f35\u003cextra\u003e\u003c\u002fextra\u003e","marker":{"color":"#16a34a"},"orientation":"h","text":["7,164","7,388","9,199","9,931","10,811","11,036","11,075","11,119","11,418","11,482","11,950","11,991","13,980","17,362","18,510","20,639","23,429","27,580","31,582","33,755"],"textposition":"auto","x":[7164,7388,9199,9931,10811,11036,11075,11119,11418,11482,11950,11991,13980,17362,18510,20639,23429,27580,31582,33755],"y":["\u6771\u548c\u92fc\u9435 2006","\u5a01\u76db 2388","\u6f22\u78ca 3707","\u53f0\u534a 5425","\u65e5\u6708\u5149\u6295\u63a7 3711","\u4e2d\u4fe1\u91d1 2891","\u5b8f\u7881 2353","\u5408\u5eab\u91d1 5880","\u7cbe\u6750 3374","\u5357\u96fb 8046","\u5357\u8302 8150","\u53f0\u4e2d\u9280 2812","\u5f37\u8302 2481","\u81fa\u4f01\u9280 2834","\u5f70\u9280 2801","\u53f0\u65b0\u65b0\u5149\u91d1 2887","\u51f1\u57fa\u91d1 2883","\u806f\u96fb 2303","\u4eac\u5143\u96fb\u5b50 2449","\u83ef\u822a 2610"],"type":"bar","xaxis":"x","yaxis":"y"},{"hovertemplate":"%{y}\u003cbr\u003e%{text} \u5f35\u003cextra\u003e\u003c\u002fextra\u003e","marker":{"color":"#dc2626"},"orientation":"h","text":["-11,592","-12,040","-12,900","-13,711","-14,053","-14,393","-14,929","-16,415","-20,144","-20,307","-20,709","-21,476","-23,555","-24,432","-25,100","-25,807","-27,499","-28,756","-32,412","-38,612"],"textposition":"auto","x":[11592,12040,12900,13711,14053,14393,14929,16415,20144,20307,20709,21476,23555,24432,25100,25807,27499,28756,32412,38612],"y":["\u53f0\u5316 1326","\u81f3\u4e0a 8112","\u83ef\u901a 2313","\u6c38\u8c50\u91d1 2890","\u529b\u7a4d\u96fb 6770","\u5f69\u6676 6116","\u53f0\u6ce5 1101","\u5357\u4e9e 1303","\u4e2d\u92fc 2002","\u7def\u5275 3231","\u83ef\u5357\u91d1 2880","\u83ef\u65b0 1605","\u5357\u4e9e\u79d1 2408","\u7fa4\u5275 3481","\u83ef\u90a6\u96fb 2344","\u9060\u50b3 4904","\u5146\u8c50\u91d1 2886","\u53cb\u9054 2409","\u9d3b\u6d77 2317","\u53f0\u73bb 1802"],"type":"bar","xaxis":"x2","yaxis":"y2"}],"layout":{"template":{"data":{"histogram2dcontour":[{"type":"histogram2dcontour","colorbar":{"outlinewidth":0,"ticks":""},"colorscale":[[0.0,"#0d0887"],[0.1111111111111111,"#46039f"],[0.2222222222222222,"#7201a8"],[0.3333333333333333,"#9c179e"],[0.4444444444444444,"#bd3786"],[0.5555555555555556,"#d8576b"],[0.6666666666666666,"#ed7953"],[0.7777777777777778,"#fb9f3a"],[0.8888888888888888,"#fdca26"],[1.0,"#f0f921"]]}],"choropleth":[{"type":"choropleth","colorbar":{"outlinewidth":0,"ticks":""}}],"histogram2d":[{"type":"histogram2d","colorbar":{"outlinewidth":0,"ticks":""},"colorscale":[[0.0,"#0d0887"],[0.1111111111111111,"#46039f"],[0.2222222222222222,"#7201a8"],[0.3333333333333333,"#9c179e"],[0.4444444444444444,"#bd3786"],[0.5555555555555556,"#d8576b"],[0.6666666666666666,"#ed7953"],[0.7777777777777778,"#fb9f3a"],[0.8888888888888888,"#fdca26"],[1.0,"#f0f921"]]}],"heatmap":[{"type":"heatmap","colorbar":{"outlinewidth":0,"ticks":""},"colorscale":[[0.0,"#0d0887"],[0.1111111111111111,"#46039f"],[0.2222222222222222,"#7201a8"],[0.3333333333333333,"#9c179e"],[0.4444444444444444,"#bd3786"],[0.5555555555555556,"#d8576b"],[0.6666666666666666,"#ed7953"],[0.7777777777777778,"#fb9f3a"],[0.8888888888888888,"#fdca26"],[1.0,"#f0f921"]]}],"contourcarpet":[{"type":"contourcarpet","colorbar":{"outlinewidth":0,"ticks":""}}],"contour":[{"type":"contour","colorbar":{"outlinewidth":0,"ticks":""},"colorscale":[[0.0,"#0d0887"],[0.1111111111111111,"#46039f"],[0.2222222222222222,"#7201a8"],[0.3333333333333333,"#9c179e"],[0.4444444444444444,"#bd3786"],[0.5555555555555556,"#d8576b"],[0.6666666666666666,"#ed7953"],[0.7777777777777778,"#fb9f3a"],[0.8888888888888888,"#fdca26"],[1.0,"#f0f921"]]}],"surface":[{"type":"surface","colorbar":{"outlinewidth":0,"ticks":""},"colorscale":[[0.0,"#0d0887"],[0.1111111111111111,"#46039f"],[0.2222222222222222,"#7201a8"],[0.3333333333333333,"#9c179e"],[0.4444444444444444,"#bd3786"],[0.5555555555555556,"#d8576b"],[0.6666666666666666,"#ed7953"],[0.7777777777777778,"#fb9f3a"],[0.8888888888888888,"#fdca26"],[1.0,"#f0f921"]]}],"mesh3d":[{"type":"mesh3d","colorbar":{"outlinewidth":0,"ticks":""}}],"scatter":[{"fillpattern":{"fillmode":"overlay","size":10,"solidity":0.2},"type":"scatter"}],"parcoords":[{"type":"parcoords","line":{"colorbar":{"outlinewidth":0,"ticks":""}}}],"scatterpolargl":[{"type":"scatterpolargl","marker":{"colorbar":{"outlinewidth":0,"ticks":""}}}],"bar":[{"error_x":{"color":"#2a3f5f"},"error_y":{"color":"#2a3f5f"},"marker":{"line":{"color":"#E5ECF6","width":0.5},"pattern":{"fillmode":"overlay","size":10,"solidity":0.2}},"type":"bar"}],"scattergeo":[{"type":"scattergeo","marker":{"colorbar":{"outlinewidth":0,"ticks":""}}}],"scatterpolar":[{"type":"scatterpolar","marker":{"colorbar":{"outlinewidth":0,"ticks":""}}}],"histogram":[{"marker":{"pattern":{"fillmode":"overlay","size":10,"solidity":0.2}},"type":"histogram"}],"scattergl":[{"type":"scattergl","marker":{"colorbar":{"outlinewidth":0,"ticks":""}}}],"scatter3d":[{"type":"scatter3d","line":{"colorbar":{"outlinewidth":0,"ticks":""}},"marker":{"colorbar":{"outlinewidth":0,"ticks":""}}}],"scattermap":[{"type":"scattermap","marker":{"colorbar":{"outlinewidth":0,"ticks":""}}}],"scattermapbox":[{"type":"scattermapbox","marker":{"colorbar":{"outlinewidth":0,"ticks":""}}}],"scatterternary":[{"type":"scatterternary","marker":{"colorbar":{"outlinewidth":0,"ticks":""}}}],"scattercarpet":[{"type":"scattercarpet","marker":{"colorbar":{"outlinewidth":0,"ticks":""}}}],"carpet":[{"aaxis":{"endlinecolor":"#2a3f5f","gridcolor":"white","linecolor":"white","minorgridcolor":"white","startlinecolor":"#2a3f5f"},"baxis":{"endlinecolor":"#2a3f5f","gridcolor":"white","linecolor":"white","minorgridcolor":"white","startlinecolor":"#2a3f5f"},"type":"carpet"}],"table":[{"cells":{"fill":{"color":"#EBF0F8"},"line":{"color":"white"}},"header":{"fill":{"color":"#C8D4E3"},"line":{"color":"white"}},"type":"table"}],"barpolar":[{"marker":{"line":{"color":"#E5ECF6","width":0.5},"pattern":{"fillmode":"overlay","size":10,"solidity":0.2}},"type":"barpolar"}],"pie":[{"automargin":true,"type":"pie"}]},"layout":{"autotypenumbers":"strict","colorway":["#636efa","#EF553B","#00cc96","#ab63fa","#FFA15A","#19d3f3","#FF6692","#B6E880","#FF97FF","#FECB52"],"font":{"color":"#2a3f5f"},"hovermode":"closest","hoverlabel":{"align":"left"},"paper_bgcolor":"white","plot_bgcolor":"#E5ECF6","polar":{"bgcolor":"#E5ECF6","angularaxis":{"gridcolor":"white","linecolor":"white","ticks":""},"radialaxis":{"gridcolor":"white","linecolor":"white","ticks":""}},"ternary":{"bgcolor":"#E5ECF6","aaxis":{"gridcolor":"white","linecolor":"white","ticks":""},"baxis":{"gridcolor":"white","linecolor":"white","ticks":""},"caxis":{"gridcolor":"white","linecolor":"white","ticks":""}},"coloraxis":{"colorbar":{"outlinewidth":0,"ticks":""}},"colorscale":{"sequential":[[0.0,"#0d0887"],[0.1111111111111111,"#46039f"],[0.2222222222222222,"#7201a8"],[0.3333333333333333,"#9c179e"],[0.4444444444444444,"#bd3786"],[0.5555555555555556,"#d8576b"],[0.6666666666666666,"#ed7953"],[0.7777777777777778,"#fb9f3a"],[0.8888888888888888,"#fdca26"],[1.0,"#f0f921"]],"sequentialminus":[[0.0,"#0d0887"],[0.1111111111111111,"#46039f"],[0.2222222222222222,"#7201a8"],[0.3333333333333333,"#9c179e"],[0.4444444444444444,"#bd3786"],[0.5555555555555556,"#d8576b"],[0.6666666666666666,"#ed7953"],[0.7777777777777778,"#fb9f3a"],[0.8888888888888888,"#fdca26"],[1.0,"#f0f921"]],"diverging":[[0,"#8e0152"],[0.1,"#c51b7d"],[0.2,"#de77ae"],[0.3,"#f1b6da"],[0.4,"#fde0ef"],[0.5,"#f7f7f7"],[0.6,"#e6f5d0"],[0.7,"#b8e186"],[0.8,"#7fbc41"],[0.9,"#4d9221"],[1,"#276419"]]},"xaxis":{"gridcolor":"white","linecolor":"white","ticks":"","title":{"standoff":15},"zerolinecolor":"white","automargin":true,"zerolinewidth":2},"yaxis":{"gridcolor":"white","linecolor":"white","ticks":"","title":{"standoff":15},"zerolinecolor":"white","automargin":true,"zerolinewidth":2},"scene":{"xaxis":{"backgroundcolor":"#E5ECF6","gridcolor":"white","linecolor":"white","showbackground":true,"ticks":"","zerolinecolor":"white","gridwidth":2},"yaxis":{"backgroundcolor":"#E5ECF6","gridcolor":"white","linecolor":"white","showbackground":true,"ticks":"","zerolinecolor":"white","gridwidth":2},"zaxis":{"backgroundcolor":"#E5ECF6","gridcolor":"white","linecolor":"white","showbackground":true,"ticks":"","zerolinecolor":"white","gridwidth":2}},"shapedefaults":{"line":{"color":"#2a3f5f"}},"annotationdefaults":{"arrowcolor":"#2a3f5f","arrowhead":0,"arrowwidth":1},"geo":{"bgcolor":"white","landcolor":"#E5ECF6","subunitcolor":"white","showland":true,"showlakes":true,"lakecolor":"white"},"title":{"x":0.05},"mapbox":{"style":"light"}}},"xaxis":{"anchor":"y","domain":[0.0,0.4],"title":{"text":"\u5f35"}},"yaxis":{"anchor":"x","domain":[0.0,1.0],"tickfont":{"size":11}},"xaxis2":{"anchor":"y2","domain":[0.6000000000000001,1.0],"title":{"text":"\u5f35"}},"yaxis2":{"anchor":"x2","domain":[0.0,1.0],"tickfont":{"size":11}},"annotations":[{"font":{"size":16},"showarrow":false,"text":"\ud83d\udfe2 \u8cb7\u8d85 Top20","x":0.2,"xanchor":"center","xref":"paper","y":1.0,"yanchor":"bottom","yref":"paper"},{"font":{"size":16},"showarrow":false,"text":"\ud83d\udd34 \u8ce3\u8d85 Top20","x":0.8,"xanchor":"center","xref":"paper","y":1.0,"yanchor":"bottom","yref":"paper"}],"font":{"family":"Microsoft JhengHei, Noto Sans TC, Arial"},"margin":{"l":150,"r":30,"t":70,"b":45},"title":{"text":"\u5916\u8cc7\u00b7\u7576\u65e5\uff082026-06-23\uff09\u524d20\u5927\u8cb7\u8ce3\u8d85 \uff5c \u55ae\u4f4d\uff1a\u5f35"},"showlegend":false,"paper_bgcolor":"white","plot_bgcolor":"white"}}