{"data":[{"hovertemplate":"%{y}\u003cbr\u003e%{x:,} \u5f35\u003cextra\u003e\u003c\u002fextra\u003e","marker":{"color":"#16a34a"},"orientation":"h","text":["76,018","79,503","80,929","104,541","108,785","109,102","115,721","118,237","130,409","137,733","140,524","142,591","144,419","158,737","177,084","182,278","217,069","248,960","287,661","487,475"],"textposition":"auto","x":[76018,79503,80929,104541,108785,109102,115721,118237,130409,137733,140524,142591,144419,158737,177084,182278,217069,248960,287661,487475],"y":["\u5927\u806f\u5927 3702","\u5143\u5927\u91d1 2885","\u4eac\u5143\u96fb\u5b50 2449","\u5927\u6210\u92fc 2027","\u65fa\u5b8f 2337","\u5408\u5eab\u91d1 5880","\u4e09\u5546\u58fd 2867","\u83ef\u822a 2610","\u5357\u4e9e\u79d1 2408","\u5357\u4e9e 1303","\u5f70\u9280 2801","\u7389\u5c71\u91d1 2884","\u7b2c\u4e00\u91d1 2892","\u570b\u6cf0\u91d1 2882","\u53f0\u5851 1301","\u81fa\u4f01\u9280 2834","\u967d\u660e 2609","\u4e2d\u92fc 2002","\u6c38\u8c50\u91d1 2890","\u806f\u96fb 2303"],"type":"bar","xaxis":"x","yaxis":"y"},{"hovertemplate":"%{y}\u003cbr\u003e%{text} \u5f35\u003cextra\u003e\u003c\u002fextra\u003e","marker":{"color":"#dc2626"},"orientation":"h","text":["-71,688","-78,904","-80,230","-81,908","-93,488","-94,381","-97,060","-102,531","-119,135","-127,645","-132,972","-133,899","-144,604","-154,956","-157,527","-178,067","-199,898","-279,113","-355,239","-612,082"],"textposition":"auto","x":[71688,78904,80230,81908,93488,94381,97060,102531,119135,127645,132972,133899,144604,154956,157527,178067,199898,279113,355239,612082],"y":["\u570b\u5de8* 2327","\u5f69\u6676 6116","\u9060\u50b3 4904","\u9577\u69ae 2603","\u548c\u78a9 4938","\u6771\u5143 1504","\u5bf6\u6210 9904","\u7d71\u4e00\u8b49 2855","\u4ec1\u5bf6 2324","\u5146\u8c50\u91d1 2886","\u53f0\u6ce5 1101","\u9060\u6771\u65b0 1402","\u83ef\u90a6\u96fb 2344","\u6b63\u65b0 2105","\u529b\u7a4d\u96fb 6770","\u53cb\u9054 2409","\u5ee3\u9054 2382","\u83ef\u5357\u91d1 2880","\u7fa4\u5275 3481","\u51f1\u57fa\u91d1 2883"],"type":"bar","xaxis":"x2","yaxis":"y2"}],"layout":{"template":{"data":{"histogram2dcontour":[{"type":"histogram2dcontour","colorbar":{"outlinewidth":0,"ticks":""},"colorscale":[[0.0,"#0d0887"],[0.1111111111111111,"#46039f"],[0.2222222222222222,"#7201a8"],[0.3333333333333333,"#9c179e"],[0.4444444444444444,"#bd3786"],[0.5555555555555556,"#d8576b"],[0.6666666666666666,"#ed7953"],[0.7777777777777778,"#fb9f3a"],[0.8888888888888888,"#fdca26"],[1.0,"#f0f921"]]}],"choropleth":[{"type":"choropleth","colorbar":{"outlinewidth":0,"ticks":""}}],"histogram2d":[{"type":"histogram2d","colorbar":{"outlinewidth":0,"ticks":""},"colorscale":[[0.0,"#0d0887"],[0.1111111111111111,"#46039f"],[0.2222222222222222,"#7201a8"],[0.3333333333333333,"#9c179e"],[0.4444444444444444,"#bd3786"],[0.5555555555555556,"#d8576b"],[0.6666666666666666,"#ed7953"],[0.7777777777777778,"#fb9f3a"],[0.8888888888888888,"#fdca26"],[1.0,"#f0f921"]]}],"heatmap":[{"type":"heatmap","colorbar":{"outlinewidth":0,"ticks":""},"colorscale":[[0.0,"#0d0887"],[0.1111111111111111,"#46039f"],[0.2222222222222222,"#7201a8"],[0.3333333333333333,"#9c179e"],[0.4444444444444444,"#bd3786"],[0.5555555555555556,"#d8576b"],[0.6666666666666666,"#ed7953"],[0.7777777777777778,"#fb9f3a"],[0.8888888888888888,"#fdca26"],[1.0,"#f0f921"]]}],"contourcarpet":[{"type":"contourcarpet","colorbar":{"outlinewidth":0,"ticks":""}}],"contour":[{"type":"contour","colorbar":{"outlinewidth":0,"ticks":""},"colorscale":[[0.0,"#0d0887"],[0.1111111111111111,"#46039f"],[0.2222222222222222,"#7201a8"],[0.3333333333333333,"#9c179e"],[0.4444444444444444,"#bd3786"],[0.5555555555555556,"#d8576b"],[0.6666666666666666,"#ed7953"],[0.7777777777777778,"#fb9f3a"],[0.8888888888888888,"#fdca26"],[1.0,"#f0f921"]]}],"surface":[{"type":"surface","colorbar":{"outlinewidth":0,"ticks":""},"colorscale":[[0.0,"#0d0887"],[0.1111111111111111,"#46039f"],[0.2222222222222222,"#7201a8"],[0.3333333333333333,"#9c179e"],[0.4444444444444444,"#bd3786"],[0.5555555555555556,"#d8576b"],[0.6666666666666666,"#ed7953"],[0.7777777777777778,"#fb9f3a"],[0.8888888888888888,"#fdca26"],[1.0,"#f0f921"]]}],"mesh3d":[{"type":"mesh3d","colorbar":{"outlinewidth":0,"ticks":""}}],"scatter":[{"fillpattern":{"fillmode":"overlay","size":10,"solidity":0.2},"type":"scatter"}],"parcoords":[{"type":"parcoords","line":{"colorbar":{"outlinewidth":0,"ticks":""}}}],"scatterpolargl":[{"type":"scatterpolargl","marker":{"colorbar":{"outlinewidth":0,"ticks":""}}}],"bar":[{"error_x":{"color":"#2a3f5f"},"error_y":{"color":"#2a3f5f"},"marker":{"line":{"color":"#E5ECF6","width":0.5},"pattern":{"fillmode":"overlay","size":10,"solidity":0.2}},"type":"bar"}],"scattergeo":[{"type":"scattergeo","marker":{"colorbar":{"outlinewidth":0,"ticks":""}}}],"scatterpolar":[{"type":"scatterpolar","marker":{"colorbar":{"outlinewidth":0,"ticks":""}}}],"histogram":[{"marker":{"pattern":{"fillmode":"overlay","size":10,"solidity":0.2}},"type":"histogram"}],"scattergl":[{"type":"scattergl","marker":{"colorbar":{"outlinewidth":0,"ticks":""}}}],"scatter3d":[{"type":"scatter3d","line":{"colorbar":{"outlinewidth":0,"ticks":""}},"marker":{"colorbar":{"outlinewidth":0,"ticks":""}}}],"scattermap":[{"type":"scattermap","marker":{"colorbar":{"outlinewidth":0,"ticks":""}}}],"scattermapbox":[{"type":"scattermapbox","marker":{"colorbar":{"outlinewidth":0,"ticks":""}}}],"scatterternary":[{"type":"scatterternary","marker":{"colorbar":{"outlinewidth":0,"ticks":""}}}],"scattercarpet":[{"type":"scattercarpet","marker":{"colorbar":{"outlinewidth":0,"ticks":""}}}],"carpet":[{"aaxis":{"endlinecolor":"#2a3f5f","gridcolor":"white","linecolor":"white","minorgridcolor":"white","startlinecolor":"#2a3f5f"},"baxis":{"endlinecolor":"#2a3f5f","gridcolor":"white","linecolor":"white","minorgridcolor":"white","startlinecolor":"#2a3f5f"},"type":"carpet"}],"table":[{"cells":{"fill":{"color":"#EBF0F8"},"line":{"color":"white"}},"header":{"fill":{"color":"#C8D4E3"},"line":{"color":"white"}},"type":"table"}],"barpolar":[{"marker":{"line":{"color":"#E5ECF6","width":0.5},"pattern":{"fillmode":"overlay","size":10,"solidity":0.2}},"type":"barpolar"}],"pie":[{"automargin":true,"type":"pie"}]},"layout":{"autotypenumbers":"strict","colorway":["#636efa","#EF553B","#00cc96","#ab63fa","#FFA15A","#19d3f3","#FF6692","#B6E880","#FF97FF","#FECB52"],"font":{"color":"#2a3f5f"},"hovermode":"closest","hoverlabel":{"align":"left"},"paper_bgcolor":"white","plot_bgcolor":"#E5ECF6","polar":{"bgcolor":"#E5ECF6","angularaxis":{"gridcolor":"white","linecolor":"white","ticks":""},"radialaxis":{"gridcolor":"white","linecolor":"white","ticks":""}},"ternary":{"bgcolor":"#E5ECF6","aaxis":{"gridcolor":"white","linecolor":"white","ticks":""},"baxis":{"gridcolor":"white","linecolor":"white","ticks":""},"caxis":{"gridcolor":"white","linecolor":"white","ticks":""}},"coloraxis":{"colorbar":{"outlinewidth":0,"ticks":""}},"colorscale":{"sequential":[[0.0,"#0d0887"],[0.1111111111111111,"#46039f"],[0.2222222222222222,"#7201a8"],[0.3333333333333333,"#9c179e"],[0.4444444444444444,"#bd3786"],[0.5555555555555556,"#d8576b"],[0.6666666666666666,"#ed7953"],[0.7777777777777778,"#fb9f3a"],[0.8888888888888888,"#fdca26"],[1.0,"#f0f921"]],"sequentialminus":[[0.0,"#0d0887"],[0.1111111111111111,"#46039f"],[0.2222222222222222,"#7201a8"],[0.3333333333333333,"#9c179e"],[0.4444444444444444,"#bd3786"],[0.5555555555555556,"#d8576b"],[0.6666666666666666,"#ed7953"],[0.7777777777777778,"#fb9f3a"],[0.8888888888888888,"#fdca26"],[1.0,"#f0f921"]],"diverging":[[0,"#8e0152"],[0.1,"#c51b7d"],[0.2,"#de77ae"],[0.3,"#f1b6da"],[0.4,"#fde0ef"],[0.5,"#f7f7f7"],[0.6,"#e6f5d0"],[0.7,"#b8e186"],[0.8,"#7fbc41"],[0.9,"#4d9221"],[1,"#276419"]]},"xaxis":{"gridcolor":"white","linecolor":"white","ticks":"","title":{"standoff":15},"zerolinecolor":"white","automargin":true,"zerolinewidth":2},"yaxis":{"gridcolor":"white","linecolor":"white","ticks":"","title":{"standoff":15},"zerolinecolor":"white","automargin":true,"zerolinewidth":2},"scene":{"xaxis":{"backgroundcolor":"#E5ECF6","gridcolor":"white","linecolor":"white","showbackground":true,"ticks":"","zerolinecolor":"white","gridwidth":2},"yaxis":{"backgroundcolor":"#E5ECF6","gridcolor":"white","linecolor":"white","showbackground":true,"ticks":"","zerolinecolor":"white","gridwidth":2},"zaxis":{"backgroundcolor":"#E5ECF6","gridcolor":"white","linecolor":"white","showbackground":true,"ticks":"","zerolinecolor":"white","gridwidth":2}},"shapedefaults":{"line":{"color":"#2a3f5f"}},"annotationdefaults":{"arrowcolor":"#2a3f5f","arrowhead":0,"arrowwidth":1},"geo":{"bgcolor":"white","landcolor":"#E5ECF6","subunitcolor":"white","showland":true,"showlakes":true,"lakecolor":"white"},"title":{"x":0.05},"mapbox":{"style":"light"}}},"xaxis":{"anchor":"y","domain":[0.0,0.4],"title":{"text":"\u5f35"}},"yaxis":{"anchor":"x","domain":[0.0,1.0],"tickfont":{"size":11}},"xaxis2":{"anchor":"y2","domain":[0.6000000000000001,1.0],"title":{"text":"\u5f35"}},"yaxis2":{"anchor":"x2","domain":[0.0,1.0],"tickfont":{"size":11}},"annotations":[{"font":{"size":16},"showarrow":false,"text":"\ud83d\udfe2 \u8cb7\u8d85 Top20","x":0.2,"xanchor":"center","xref":"paper","y":1.0,"yanchor":"bottom","yref":"paper"},{"font":{"size":16},"showarrow":false,"text":"\ud83d\udd34 \u8ce3\u8d85 Top20","x":0.8,"xanchor":"center","xref":"paper","y":1.0,"yanchor":"bottom","yref":"paper"}],"font":{"family":"Microsoft JhengHei, Noto Sans TC, Arial"},"margin":{"l":150,"r":30,"t":70,"b":45},"title":{"text":"\u5916\u8cc7\u00b7\u8fd120\u65e5(\u6708)\uff082026-05-26 ~ 2026-06-23\uff09\u524d20\u5927\u8cb7\u8ce3\u8d85 \uff5c \u55ae\u4f4d\uff1a\u5f35"},"showlegend":false,"paper_bgcolor":"white","plot_bgcolor":"white"}}