{"data":[{"hovertemplate":"%{y}\u003cbr\u003e%{x:,} \u5f35\u003cextra\u003e\u003c\u002fextra\u003e","marker":{"color":"#16a34a"},"orientation":"h","text":["26,840","28,650","29,182","31,155","34,274","38,328","42,246","42,795","44,331","48,904","50,099","54,179","54,826","68,858","70,577","101,600","109,252","145,935","181,299","355,369"],"textposition":"auto","x":[26840,28650,29182,31155,34274,38328,42246,42795,44331,48904,50099,54179,54826,68858,70577,101600,109252,145935,181299,355369],"y":["\u7fa4\u76ca\u8b49 6005","\u4eac\u5143\u96fb\u5b50 2449","\u5eb7\u9708* 6919","\u5143\u5927\u91d1 2885","\u65e5\u6708\u5149\u6295\u63a7 3711","\u65fa\u5b8f 2337","\u5357\u4e9e 1303","\u53f0\u5316 1326","\u4e2d\u4fe1\u91d1 2891","\u5357\u4e9e\u79d1 2408","\u5408\u5eab\u91d1 5880","\u53f0\u65b0\u65b0\u5149\u91d1 2887","\u83ef\u822a 2610","\u51f1\u57fa\u91d1 2883","\u6c38\u8c50\u91d1 2890","\u53cb\u9054 2409","\u53f0\u73bb 1802","\u9577\u69ae\u822a 2618","\u53f0\u5851 1301","\u4e2d\u92fc 2002"],"type":"bar","xaxis":"x","yaxis":"y"},{"hovertemplate":"%{y}\u003cbr\u003e%{text} \u5f35\u003cextra\u003e\u003c\u002fextra\u003e","marker":{"color":"#dc2626"},"orientation":"h","text":["-17,631","-17,659","-21,544","-22,924","-23,097","-23,180","-26,933","-28,284","-29,273","-29,832","-40,335","-42,270","-42,557","-42,983","-68,651","-80,136","-80,585","-87,451","-97,566","-172,925"],"textposition":"auto","x":[17631,17659,21544,22924,23097,23180,26933,28284,29273,29832,40335,42270,42557,42983,68651,80136,80585,87451,97566,172925],"y":["\u5408\u6676 6182","\u9060\u6771\u9280 2845","\u570b\u78a9 2406","\u53f0\u7063\u9ad8\u9435 2633","\u529b\u6210 6239","\u7d71\u4e00 1216","\u4e0a\u6d77\u5546\u9280 5876","\u81fb\u9f0e-KY 4958","\u9d3b\u6d77 2317","\u806f\u5408\u518d\u751f 3576","\u9060\u50b3 4904","\u53f0\u6ce5 1101","\u5bf6\u6210 9904","\u4ec1\u5bf6 2324","\u7def\u5275 3231","\u5146\u8c50\u91d1 2886","\u83ef\u90a6\u96fb 2344","\u5f69\u6676 6116","\u529b\u7a4d\u96fb 6770","\u7fa4\u5275 3481"],"type":"bar","xaxis":"x2","yaxis":"y2"}],"layout":{"template":{"data":{"histogram2dcontour":[{"type":"histogram2dcontour","colorbar":{"outlinewidth":0,"ticks":""},"colorscale":[[0.0,"#0d0887"],[0.1111111111111111,"#46039f"],[0.2222222222222222,"#7201a8"],[0.3333333333333333,"#9c179e"],[0.4444444444444444,"#bd3786"],[0.5555555555555556,"#d8576b"],[0.6666666666666666,"#ed7953"],[0.7777777777777778,"#fb9f3a"],[0.8888888888888888,"#fdca26"],[1.0,"#f0f921"]]}],"choropleth":[{"type":"choropleth","colorbar":{"outlinewidth":0,"ticks":""}}],"histogram2d":[{"type":"histogram2d","colorbar":{"outlinewidth":0,"ticks":""},"colorscale":[[0.0,"#0d0887"],[0.1111111111111111,"#46039f"],[0.2222222222222222,"#7201a8"],[0.3333333333333333,"#9c179e"],[0.4444444444444444,"#bd3786"],[0.5555555555555556,"#d8576b"],[0.6666666666666666,"#ed7953"],[0.7777777777777778,"#fb9f3a"],[0.8888888888888888,"#fdca26"],[1.0,"#f0f921"]]}],"heatmap":[{"type":"heatmap","colorbar":{"outlinewidth":0,"ticks":""},"colorscale":[[0.0,"#0d0887"],[0.1111111111111111,"#46039f"],[0.2222222222222222,"#7201a8"],[0.3333333333333333,"#9c179e"],[0.4444444444444444,"#bd3786"],[0.5555555555555556,"#d8576b"],[0.6666666666666666,"#ed7953"],[0.7777777777777778,"#fb9f3a"],[0.8888888888888888,"#fdca26"],[1.0,"#f0f921"]]}],"contourcarpet":[{"type":"contourcarpet","colorbar":{"outlinewidth":0,"ticks":""}}],"contour":[{"type":"contour","colorbar":{"outlinewidth":0,"ticks":""},"colorscale":[[0.0,"#0d0887"],[0.1111111111111111,"#46039f"],[0.2222222222222222,"#7201a8"],[0.3333333333333333,"#9c179e"],[0.4444444444444444,"#bd3786"],[0.5555555555555556,"#d8576b"],[0.6666666666666666,"#ed7953"],[0.7777777777777778,"#fb9f3a"],[0.8888888888888888,"#fdca26"],[1.0,"#f0f921"]]}],"surface":[{"type":"surface","colorbar":{"outlinewidth":0,"ticks":""},"colorscale":[[0.0,"#0d0887"],[0.1111111111111111,"#46039f"],[0.2222222222222222,"#7201a8"],[0.3333333333333333,"#9c179e"],[0.4444444444444444,"#bd3786"],[0.5555555555555556,"#d8576b"],[0.6666666666666666,"#ed7953"],[0.7777777777777778,"#fb9f3a"],[0.8888888888888888,"#fdca26"],[1.0,"#f0f921"]]}],"mesh3d":[{"type":"mesh3d","colorbar":{"outlinewidth":0,"ticks":""}}],"scatter":[{"fillpattern":{"fillmode":"overlay","size":10,"solidity":0.2},"type":"scatter"}],"parcoords":[{"type":"parcoords","line":{"colorbar":{"outlinewidth":0,"ticks":""}}}],"scatterpolargl":[{"type":"scatterpolargl","marker":{"colorbar":{"outlinewidth":0,"ticks":""}}}],"bar":[{"error_x":{"color":"#2a3f5f"},"error_y":{"color":"#2a3f5f"},"marker":{"line":{"color":"#E5ECF6","width":0.5},"pattern":{"fillmode":"overlay","size":10,"solidity":0.2}},"type":"bar"}],"scattergeo":[{"type":"scattergeo","marker":{"colorbar":{"outlinewidth":0,"ticks":""}}}],"scatterpolar":[{"type":"scatterpolar","marker":{"colorbar":{"outlinewidth":0,"ticks":""}}}],"histogram":[{"marker":{"pattern":{"fillmode":"overlay","size":10,"solidity":0.2}},"type":"histogram"}],"scattergl":[{"type":"scattergl","marker":{"colorbar":{"outlinewidth":0,"ticks":""}}}],"scatter3d":[{"type":"scatter3d","line":{"colorbar":{"outlinewidth":0,"ticks":""}},"marker":{"colorbar":{"outlinewidth":0,"ticks":""}}}],"scattermap":[{"type":"scattermap","marker":{"colorbar":{"outlinewidth":0,"ticks":""}}}],"scattermapbox":[{"type":"scattermapbox","marker":{"colorbar":{"outlinewidth":0,"ticks":""}}}],"scatterternary":[{"type":"scatterternary","marker":{"colorbar":{"outlinewidth":0,"ticks":""}}}],"scattercarpet":[{"type":"scattercarpet","marker":{"colorbar":{"outlinewidth":0,"ticks":""}}}],"carpet":[{"aaxis":{"endlinecolor":"#2a3f5f","gridcolor":"white","linecolor":"white","minorgridcolor":"white","startlinecolor":"#2a3f5f"},"baxis":{"endlinecolor":"#2a3f5f","gridcolor":"white","linecolor":"white","minorgridcolor":"white","startlinecolor":"#2a3f5f"},"type":"carpet"}],"table":[{"cells":{"fill":{"color":"#EBF0F8"},"line":{"color":"white"}},"header":{"fill":{"color":"#C8D4E3"},"line":{"color":"white"}},"type":"table"}],"barpolar":[{"marker":{"line":{"color":"#E5ECF6","width":0.5},"pattern":{"fillmode":"overlay","size":10,"solidity":0.2}},"type":"barpolar"}],"pie":[{"automargin":true,"type":"pie"}]},"layout":{"autotypenumbers":"strict","colorway":["#636efa","#EF553B","#00cc96","#ab63fa","#FFA15A","#19d3f3","#FF6692","#B6E880","#FF97FF","#FECB52"],"font":{"color":"#2a3f5f"},"hovermode":"closest","hoverlabel":{"align":"left"},"paper_bgcolor":"white","plot_bgcolor":"#E5ECF6","polar":{"bgcolor":"#E5ECF6","angularaxis":{"gridcolor":"white","linecolor":"white","ticks":""},"radialaxis":{"gridcolor":"white","linecolor":"white","ticks":""}},"ternary":{"bgcolor":"#E5ECF6","aaxis":{"gridcolor":"white","linecolor":"white","ticks":""},"baxis":{"gridcolor":"white","linecolor":"white","ticks":""},"caxis":{"gridcolor":"white","linecolor":"white","ticks":""}},"coloraxis":{"colorbar":{"outlinewidth":0,"ticks":""}},"colorscale":{"sequential":[[0.0,"#0d0887"],[0.1111111111111111,"#46039f"],[0.2222222222222222,"#7201a8"],[0.3333333333333333,"#9c179e"],[0.4444444444444444,"#bd3786"],[0.5555555555555556,"#d8576b"],[0.6666666666666666,"#ed7953"],[0.7777777777777778,"#fb9f3a"],[0.8888888888888888,"#fdca26"],[1.0,"#f0f921"]],"sequentialminus":[[0.0,"#0d0887"],[0.1111111111111111,"#46039f"],[0.2222222222222222,"#7201a8"],[0.3333333333333333,"#9c179e"],[0.4444444444444444,"#bd3786"],[0.5555555555555556,"#d8576b"],[0.6666666666666666,"#ed7953"],[0.7777777777777778,"#fb9f3a"],[0.8888888888888888,"#fdca26"],[1.0,"#f0f921"]],"diverging":[[0,"#8e0152"],[0.1,"#c51b7d"],[0.2,"#de77ae"],[0.3,"#f1b6da"],[0.4,"#fde0ef"],[0.5,"#f7f7f7"],[0.6,"#e6f5d0"],[0.7,"#b8e186"],[0.8,"#7fbc41"],[0.9,"#4d9221"],[1,"#276419"]]},"xaxis":{"gridcolor":"white","linecolor":"white","ticks":"","title":{"standoff":15},"zerolinecolor":"white","automargin":true,"zerolinewidth":2},"yaxis":{"gridcolor":"white","linecolor":"white","ticks":"","title":{"standoff":15},"zerolinecolor":"white","automargin":true,"zerolinewidth":2},"scene":{"xaxis":{"backgroundcolor":"#E5ECF6","gridcolor":"white","linecolor":"white","showbackground":true,"ticks":"","zerolinecolor":"white","gridwidth":2},"yaxis":{"backgroundcolor":"#E5ECF6","gridcolor":"white","linecolor":"white","showbackground":true,"ticks":"","zerolinecolor":"white","gridwidth":2},"zaxis":{"backgroundcolor":"#E5ECF6","gridcolor":"white","linecolor":"white","showbackground":true,"ticks":"","zerolinecolor":"white","gridwidth":2}},"shapedefaults":{"line":{"color":"#2a3f5f"}},"annotationdefaults":{"arrowcolor":"#2a3f5f","arrowhead":0,"arrowwidth":1},"geo":{"bgcolor":"white","landcolor":"#E5ECF6","subunitcolor":"white","showland":true,"showlakes":true,"lakecolor":"white"},"title":{"x":0.05},"mapbox":{"style":"light"}}},"xaxis":{"anchor":"y","domain":[0.0,0.4],"title":{"text":"\u5f35"}},"yaxis":{"anchor":"x","domain":[0.0,1.0],"tickfont":{"size":11}},"xaxis2":{"anchor":"y2","domain":[0.6000000000000001,1.0],"title":{"text":"\u5f35"}},"yaxis2":{"anchor":"x2","domain":[0.0,1.0],"tickfont":{"size":11}},"annotations":[{"font":{"size":16},"showarrow":false,"text":"\ud83d\udfe2 \u8cb7\u8d85 Top20","x":0.2,"xanchor":"center","xref":"paper","y":1.0,"yanchor":"bottom","yref":"paper"},{"font":{"size":16},"showarrow":false,"text":"\ud83d\udd34 \u8ce3\u8d85 Top20","x":0.8,"xanchor":"center","xref":"paper","y":1.0,"yanchor":"bottom","yref":"paper"}],"font":{"family":"Microsoft JhengHei, Noto Sans TC, Arial"},"margin":{"l":150,"r":30,"t":70,"b":45},"title":{"text":"\u5916\u8cc7\u00b7\u8fd15\u65e5(\u9031)\uff082026-06-15 ~ 2026-06-22\uff09\u524d20\u5927\u8cb7\u8ce3\u8d85 \uff5c \u55ae\u4f4d\uff1a\u5f35"},"showlegend":false,"paper_bgcolor":"white","plot_bgcolor":"white"}}